{
	"schemaVersion": {
		"major": 1,
		"minor": 0,
		"patch": 0,
		"readable": "Firebolt Version Manifest v1.0.0"
	},
	"capabilities": {
		"xrn:firebolt:capability:accessibility:app": {
			"level": "must",
			"use": {
				"public": true,
				"negotiable": true
			},
			"manage": {
				"public": false,
				"negotiable": false
			},
			"provide": {
				"public": false,
				"negotiable": false
			}
		},
		"xrn:firebolt:capability:accessibility:audiodescriptions": {
			"level": "must",
			"use": {
				"public": true,
				"negotiable": true
			},
			"manage": {
				"public": false,
				"negotiable": false
			},
			"provide": {
				"public": false,
				"negotiable": false
			}
		},
		"xrn:firebolt:capability:accessibility:closedcaptions": {
			"level": "must",
			"use": {
				"public": true,
				"negotiable": true
			},
			"manage": {
				"public": false,
				"negotiable": false
			},
			"provide": {
				"public": false,
				"negotiable": false
			}
		},
		"xrn:firebolt:capability:accessibility:highcontrastui": {
			"level": "must",
			"use": {
				"public": true,
				"negotiable": true
			},
			"manage": {
				"public": false,
				"negotiable": false
			},
			"provide": {
				"public": false,
				"negotiable": false
			}
		},
		"xrn:firebolt:capability:accessibility:voiceguidance": {
			"level": "must",
			"use": {
				"public": true,
				"negotiable": true
			},
			"manage": {
				"public": false,
				"negotiable": false
			},
			"provide": {
				"public": false,
				"negotiable": false
			}
		},
		"xrn:firebolt:capability:account:id": {
			"level": "could"
		},
		"xrn:firebolt:capability:account:uid": {
			"level": "should"
		},
		"xrn:firebolt:capability:advertising:configuration": {
			"level": "could"
		},
		"xrn:firebolt:capability:advertising:identifier": {
			"level": "could",
			"use": {
				"public": true,
				"negotiable": true
			},
			"manage": {
				"public": false,
				"negotiable": false
			},
			"provide": {
				"public": false,
				"negotiable": false
			}
		},
		"xrn:firebolt:capability:capabilities:info": {
			"level": "must",
			"use": {
				"public": true,
				"negotiable": false
			},
			"manage": {
				"public": false,
				"negotiable": false
			},
			"provide": {
				"public": false,
				"negotiable": false
			}
		},
		"xrn:firebolt:capability:capabilities:request": {
			"level": "must",
			"use": {
				"public": true,
				"negotiable": false
			},
			"manage": {
				"public": false,
				"negotiable": false
			},
			"provide": {
				"public": false,
				"negotiable": false
			}
		},
		"xrn:firebolt:capability:device:class": {
			"level": "must",
			"use": {
				"public": true,
				"negotiable": true
			},
			"manage": {
				"public": false,
				"negotiable": false
			},
			"provide": {
				"public": false,
				"negotiable": false
			}
		},
		"xrn:firebolt:capability:device:uid": {
			"level": "must",
			"use": {
				"public": true,
				"negotiable": true
			},
			"manage": {
				"public": false,
				"negotiable": false
			},
			"provide": {
				"public": false,
				"negotiable": false
			}
		},
		"xrn:firebolt:capability:device:uptime": {
			"level": "must",
			"use": {
				"public": true,
				"negotiable": true
			},
			"manage": {
				"public": false,
				"negotiable": false
			},
			"provide": {
				"public": false,
				"negotiable": false
			}
		},
		"xrn:firebolt:capability:discovery:sign-in-status": {
			"level": "could"
		},
		"xrn:firebolt:capability:discovery:watch-next": {
			"level": "could"
		},
		"xrn:firebolt:capability:discovery:watched": {
			"level": "could"
		},
		"xrn:firebolt:capability:display:maxresolution": {
			"level": "must",
			"use": {
				"public": true,
				"negotiable": true
			},
			"manage": {
				"public": false,
				"negotiable": false
			},
			"provide": {
				"public": false,
				"negotiable": false
			}
		},
		"xrn:firebolt:capability:display:size": {
			"level": "must",
			"use": {
				"public": true,
				"negotiable": true
			},
			"manage": {
				"public": false,
				"negotiable": false
			},
			"provide": {
				"public": false,
				"negotiable": false
			}
		},
		"xrn:firebolt:capability:grants:state": {
			"level": "should"
		},
		"xrn:firebolt:capability:input:keyboard": {
			"level": "should"
		},
		"xrn:firebolt:capability:lifecycle2:state": {
			"level": "must",
			"use": {
				"public": true,
				"negotiable": true
			},
			"manage": {
				"public": false,
				"negotiable": false
			},
			"provide": {
				"public": false,
				"negotiable": false
			}
		},
		"xrn:firebolt:capability:lifecycle:initialize": {
			"level": "must",
			"use": {
				"public": true,
				"negotiable": false
			},
			"manage": {
				"public": false,
				"negotiable": false
			},
			"provide": {
				"public": false,
				"negotiable": false
			}
		},
		"xrn:firebolt:capability:lifecycle:ready": {
			"level": "must",
			"use": {
				"public": true,
				"negotiable": false
			},
			"manage": {
				"public": false,
				"negotiable": false
			},
			"provide": {
				"public": false,
				"negotiable": false
			}
		},
		"xrn:firebolt:capability:lifecycle:state": {
			"level": "must",
			"use": {
				"public": true,
				"negotiable": false
			},
			"manage": {
				"public": true,
				"negotiable": true
			},
			"provide": {
				"public": true,
				"negotiable": true
			}
		},
		"xrn:firebolt:capability:localization:country-code": {
			"level": "must",
			"use": {
				"public": true,
				"negotiable": true
			},
			"manage": {
				"public": false,
				"negotiable": false
			},
			"provide": {
				"public": false,
				"negotiable": false
			}
		},
		"xrn:firebolt:capability:localization:language": {
			"level": "must",
			"use": {
				"public": true,
				"negotiable": true
			},
			"manage": {
				"public": false,
				"negotiable": false
			},
			"provide": {
				"public": false,
				"negotiable": false
			}
		},
		"xrn:firebolt:capability:localization:locale": {
			"level": "must",
			"use": {
				"public": true,
				"negotiable": true
			},
			"manage": {
				"public": false,
				"negotiable": false
			},
			"provide": {
				"public": false,
				"negotiable": false
			}
		},
		"xrn:firebolt:capability:localization:locality": {
			"level": "could"
		},
		"xrn:firebolt:capability:localization:location": {
			"level": "could"
		},
		"xrn:firebolt:capability:localization:postal-code": {
			"level": "could"
		},
		"xrn:firebolt:capability:localization:time-zone": {
			"level": "could"
		},
		"xrn:firebolt:capability:metrics:distributor": {
			"level": "could"
		},
		"xrn:firebolt:capability:privacy:settings": {
			"level": "could"
		},
		"xrn:firebolt:capability:protocol:dial": {
			"level": "could"
		},
		"xrn:firebolt:capability:protocol:wifi": {
			"level": "could"
		},
		"xrn:firebolt:capability:rpc:discover": {
			"level": "must",
			"use": {
				"public": true,
				"negotiable": true
			},
			"manage": {
				"public": false,
				"negotiable": false
			},
			"provide": {
				"public": false,
				"negotiable": false
			}
		},
		"xrn:firebolt:capability:secondscreen:protocol": {
			"level": "should"
		},
		"xrn:firebolt:capability:storage:secure": {
			"level": "could"
		},
		"xrn:firebolt:capability:token:account": {
			"level": "should"
		},
		"xrn:firebolt:capability:token:device": {
			"level": "should"
		},
		"xrn:firebolt:capability:token:platform": {
			"level": "should"
		},
		"xrn:firebolt:capability:token:root": {
			"level": "should"
		},
		"xrn:firebolt:capability:token:session": {
			"level": "should"
		},
		"xrn:firebolt:capability:usergrant:acknowledgechallenge": {
			"level": "should"
		},
		"xrn:firebolt:capability:usergrant:pinchallenge": {
			"level": "should"
		}
	},
	"apis": {
		"1": {
			"openrpc": "1.2.4",
			"info": {
				"title": "Firebolt JSON-RPC API",
				"version": "1.8.0-next.11",
				"x-module-descriptions": {
					"Internal": "Internal methods for SDK / FEE integration",
					"Accessibility": "The `Accessibility` module provides access to the user/device settings for closed captioning and voice guidance.\n\nApps **SHOULD** attempt o respect these settings, rather than manage and persist seprate settings, which would be different per-app.",
					"Advertising": "A module for platform provided advertising settings and functionality.",
					"Device": "A module for querying about the device and it's capabilities.",
					"Display": "A module for querying about the display",
					"Lifecycle2": "Methods and events for responding to Lifecycle changes in your app.",
					"Localization": "Methods for accessing location and language preferences.",
					"Stats": "Provides methods to retrieve application-level system information."
				}
			},
			"methods": [
				{
					"name": "rpc.discover",
					"summary": "The OpenRPC schema for this JSON-RPC API",
					"params": [],
					"tags": [
						{
							"name": "capabilities",
							"x-uses": [
								"xrn:firebolt:capability:rpc:discover"
							]
						}
					],
					"result": {
						"name": "OpenRPC Schema",
						"schema": {
							"type": "object"
						}
					},
					"examples": [
						{
							"name": "Default",
							"params": [],
							"result": {
								"name": "schema",
								"value": {}
							}
						}
					]
				},
				{
					"name": "Internal.initialize",
					"tags": [
						{
							"name": "rpc-only"
						},
						{
							"name": "capabilities",
							"x-uses": [
								"xrn:firebolt:capability:lifecycle:initialize"
							]
						}
					],
					"summary": "Initialize the SDK / FEE session.",
					"description": "A single version of the Firebolt SDK is compiled into each app. When an app starts up, the SDK **MUST** call this method as soon as possible and **before** any other JSON-RPC methods are sent.",
					"params": [
						{
							"name": "version",
							"required": true,
							"schema": {
								"$ref": "#/x-schemas/Types/SemanticVersion"
							},
							"summary": "The semantic version of the SDK."
						}
					],
					"result": {
						"name": "session",
						"summary": "Info about the SDK/FEE session",
						"schema": {
							"$ref": "#/components/schemas/InitializeResult"
						}
					},
					"examples": [
						{
							"name": "Default Example",
							"params": [
								{
									"name": "version",
									"value": {
										"major": 1,
										"minor": 0,
										"patch": 0,
										"readable": "Firebolt SDK 1.0.0"
									}
								}
							],
							"result": {
								"name": "Default Result",
								"value": {
									"version": {
										"major": 1,
										"minor": 0,
										"patch": 0,
										"readable": "Firebolt FEE 1.0.0"
									}
								}
							}
						}
					]
				},
				{
					"name": "Accessibility.audioDescription",
					"summary": "Returns the audio description setting of the device",
					"params": [],
					"tags": [
						{
							"name": "property:readonly"
						},
						{
							"name": "capabilities",
							"x-uses": [
								"xrn:firebolt:capability:accessibility:audiodescriptions"
							]
						}
					],
					"result": {
						"name": "setting",
						"summary": "the audio description setting",
						"schema": {
							"type": "boolean"
						}
					},
					"examples": [
						{
							"name": "Getting the audio description setting",
							"params": [],
							"result": {
								"name": "Default Result",
								"value": {
									"enabled": true
								}
							}
						}
					]
				},
				{
					"name": "Accessibility.closedCaptionsSettings",
					"summary": "Returns captions settings: enabled, and a list of zero or more languages in order of decreasing preference",
					"params": [],
					"tags": [
						{
							"name": "property:readonly"
						},
						{
							"name": "capabilities",
							"x-uses": [
								"xrn:firebolt:capability:accessibility:closedcaptions"
							]
						}
					],
					"result": {
						"name": "closedCaptionsSettings",
						"summary": "the closed captions settings",
						"schema": {
							"$ref": "#/x-schemas/Accessibility/ClosedCaptionsSettings"
						}
					},
					"examples": [
						{
							"name": "Getting the closed captions settings",
							"params": [],
							"result": {
								"name": "settings",
								"value": {
									"enabled": true,
									"styles": {
										"fontFamily": "monospaced_sanserif",
										"fontSize": 1,
										"fontColor": "#ffffff",
										"fontEdge": "none",
										"fontEdgeColor": "#7F7F7F",
										"fontOpacity": 100,
										"backgroundColor": "#000000",
										"backgroundOpacity": 100,
										"textAlign": "center",
										"textAlignVertical": "middle",
										"windowColor": "white",
										"windowOpacity": 50
									},
									"preferredLanguages": [
										"eng",
										"spa"
									]
								}
							}
						}
					]
				},
				{
					"name": "Accessibility.highContrastUI",
					"summary": "Returns the high contrast UI device setting",
					"params": [],
					"tags": [
						{
							"name": "property:readonly"
						},
						{
							"name": "capabilities",
							"x-uses": [
								"xrn:firebolt:capability:accessibility:highcontrastui"
							]
						}
					],
					"result": {
						"name": "highContrastUI",
						"summary": "Whether high-contrast UI mode is enabled",
						"schema": {
							"type": "boolean"
						}
					},
					"examples": [
						{
							"name": "High-contrast UI mode is enabled",
							"params": [],
							"result": {
								"name": "Default Result",
								"value": true
							}
						}
					]
				},
				{
					"name": "Accessibility.voiceGuidanceSettings",
					"summary": "Returns voice guidance settings: enabled, rate, and verbosity",
					"params": [],
					"tags": [
						{
							"name": "property:readonly"
						},
						{
							"name": "capabilities",
							"x-uses": [
								"xrn:firebolt:capability:accessibility:voiceguidance"
							]
						}
					],
					"result": {
						"name": "settings",
						"summary": "the voice guidance settings",
						"schema": {
							"$ref": "#/x-schemas/Accessibility/VoiceGuidanceSettings"
						}
					},
					"examples": [
						{
							"name": "Getting the voice guidance settings",
							"params": [],
							"result": {
								"name": "Default Result",
								"value": {
									"enabled": true,
									"rate": 0.8,
									"navigationHints": true
								}
							}
						}
					]
				},
				{
					"name": "Advertising.advertisingId",
					"tags": [
						{
							"name": "capabilities",
							"x-uses": [
								"xrn:firebolt:capability:advertising:identifier"
							]
						}
					],
					"summary": "Returns the IFA.",
					"params": [],
					"result": {
						"name": "advertisingId",
						"summary": "The advertising ID",
						"schema": {
							"$ref": "#/components/schemas/AdvertisingIdResult"
						}
					},
					"examples": [
						{
							"name": "Getting the advertising ID",
							"params": [],
							"result": {
								"name": "Default Result",
								"value": {
									"ifa": "bd87dd10-8d1d-4b93-b1a6-a8e5d410e400",
									"ifa_type": "sspid",
									"lmt": "0"
								}
							}
						},
						{
							"name": "Getting the advertising ID with scope browse",
							"params": [],
							"result": {
								"name": "Default Result",
								"value": {
									"ifa": "bd87dd10-8d1d-4b93-b1a6-a8e5d410e400",
									"ifa_type": "sspid",
									"lmt": "1"
								}
							}
						},
						{
							"name": "Getting the advertising ID with scope content",
							"params": [],
							"result": {
								"name": "Default Result",
								"value": {
									"ifa": "bd87dd10-8d1d-4b93-b1a6-a8e5d410e400",
									"ifa_type": "idfa",
									"lmt": "0"
								}
							}
						}
					]
				},
				{
					"name": "Device.uid",
					"summary": "Returns a persistent unique UUID for the current app and device. The UUID is reset when the app or device is reset",
					"params": [],
					"tags": [
						{
							"name": "capabilities",
							"x-uses": [
								"xrn:firebolt:capability:device:uid"
							]
						}
					],
					"result": {
						"name": "uniqueId",
						"summary": "A unique UUID for this app-device pair.",
						"schema": {
							"type": "string"
						}
					},
					"examples": [
						{
							"name": "Getting the unique UUID",
							"params": [],
							"result": {
								"name": "Default Result",
								"value": "ee6723b8-7ab3-462c-8d93-dbf61227998e"
							}
						}
					]
				},
				{
					"name": "Device.deviceClass",
					"summary": "Returns the class of the device",
					"params": [],
					"tags": [
						{
							"name": "capabilities",
							"x-uses": [
								"xrn:firebolt:capability:device:class"
							]
						}
					],
					"result": {
						"name": "deviceClass",
						"summary": "The device class",
						"schema": {
							"$ref": "#/components/schemas/DeviceClass"
						}
					},
					"examples": [
						{
							"name": "Getting the device class",
							"params": [],
							"result": {
								"name": "Default Result",
								"value": "ott"
							}
						}
					]
				},
				{
					"name": "Device.uptime",
					"summary": "Returns the number of seconds since most recent device boot, including any time spent during deep sleep",
					"params": [],
					"tags": [
						{
							"name": "capabilities",
							"x-uses": [
								"xrn:firebolt:capability:device:uptime"
							]
						}
					],
					"result": {
						"name": "uptime",
						"summary": "The device uptime",
						"schema": {
							"type": "number"
						}
					},
					"examples": [
						{
							"name": "Getting the device uptime",
							"params": [],
							"result": {
								"name": "Default Result",
								"value": 123456
							}
						}
					]
				},
				{
					"name": "Device.timeInActiveState",
					"summary": "Returns the number of seconds since the device transitioned to the ON power state",
					"params": [],
					"tags": [
						{
							"name": "capabilities",
							"x-uses": [
								"xrn:firebolt:capability:device:uptime"
							]
						}
					],
					"result": {
						"name": "timeInActiveState",
						"summary": "The device time in active state",
						"schema": {
							"type": "number"
						}
					},
					"examples": [
						{
							"name": "Getting the number of seconds since the device transitioned to the ON power state",
							"params": [],
							"result": {
								"name": "Default Result",
								"value": 654321
							}
						}
					]
				},
				{
					"name": "Display.size",
					"summary": "Returns the physical dimensions of the connected or integral display, in centimeters. Returns 0, 0 on a OTT/STB device when a display is not connected over HDMI",
					"params": [],
					"tags": [
						{
							"name": "capabilities",
							"x-uses": [
								"xrn:firebolt:capability:display:size"
							]
						}
					],
					"result": {
						"name": "size",
						"summary": "The display size in centimeters",
						"schema": {
							"type": "object",
							"properties": {
								"width": {
									"type": "integer",
									"description": "The width of the display in centimeters"
								},
								"height": {
									"type": "integer",
									"description": "The height of the display in centimeters"
								}
							}
						}
					},
					"examples": [
						{
							"name": "Getting the display size",
							"params": [],
							"result": {
								"name": "Default Result",
								"value": {
									"width": 48,
									"height": 27
								}
							}
						}
					]
				},
				{
					"name": "Display.maxResolution",
					"summary": "Returns the physical/native resolution of the connected or integral display, in pixels. Returns 0, 0 on a OTT/STB device when a display is not connected over HDMI",
					"params": [],
					"tags": [
						{
							"name": "capabilities",
							"x-uses": [
								"xrn:firebolt:capability:display:maxresolution"
							]
						}
					],
					"result": {
						"name": "maxResolution",
						"summary": "The display resolution",
						"schema": {
							"type": "object",
							"properties": {
								"width": {
									"type": "integer",
									"description": "The width of the display in pixels"
								},
								"height": {
									"type": "integer",
									"description": "The height of the display in pixels"
								}
							}
						}
					},
					"examples": [
						{
							"name": "Getting the display size",
							"params": [],
							"result": {
								"name": "Default Result",
								"value": {
									"width": 1920,
									"height": 1080
								}
							}
						}
					]
				},
				{
					"name": "Lifecycle2.close",
					"tags": [
						{
							"name": "capabilities",
							"x-uses": [
								"xrn:firebolt:capability:lifecycle2:state"
							]
						}
					],
					"summary": "Request the platform to deactivate the app, and possibly take further action.",
					"params": [
						{
							"name": "type",
							"summary": "The type of the close app is requesting",
							"required": true,
							"schema": {
								"$ref": "#/components/schemas/CloseType"
							}
						}
					],
					"result": {
						"name": "result",
						"schema": {
							"type": "null"
						}
					},
					"examples": [
						{
							"name": "Close the app when the user presses back on the app home screen",
							"params": [
								{
									"name": "type",
									"value": "unload"
								}
							],
							"result": {
								"name": "Default Result",
								"value": null
							}
						},
						{
							"name": "Close the app when the user selects an exit menu item",
							"params": [
								{
									"name": "type",
									"value": "deactivate"
								}
							],
							"result": {
								"name": "Default Result",
								"value": null
							}
						}
					]
				},
				{
					"name": "Lifecycle2.state",
					"summary": "Get the current lifecycle state of the app.",
					"tags": [
						{
							"name": "capabilities",
							"x-uses": [
								"xrn:firebolt:capability:lifecycle2:state"
							]
						}
					],
					"params": [],
					"result": {
						"name": "state",
						"summary": "The current lifecycle state of the app.",
						"schema": {
							"$ref": "#/components/schemas/LifecycleState"
						}
					},
					"examples": [
						{
							"name": "Default Example",
							"params": [],
							"result": {
								"name": "Default Result",
								"value": "active"
							}
						}
					]
				},
				{
					"name": "Localization.country",
					"tags": [
						{
							"name": "property:readonly"
						},
						{
							"name": "capabilities",
							"x-uses": [
								"xrn:firebolt:capability:localization:country-code"
							]
						}
					],
					"summary": "Returns the ISO 3166-1 alpha-2 code for the country device is located in.",
					"params": [],
					"result": {
						"name": "code",
						"summary": "The device country code.",
						"schema": {
							"$ref": "#/x-schemas/Localization/CountryCode"
						}
					},
					"examples": [
						{
							"name": "Default example",
							"params": [],
							"result": {
								"name": "Default Result",
								"value": "US"
							}
						},
						{
							"name": "Another example",
							"params": [],
							"result": {
								"name": "Default Result",
								"value": "GB"
							}
						}
					]
				},
				{
					"name": "Localization.preferredAudioLanguages",
					"summary": "Returns a list of ISO 639-2/B codes for the preferred audio languages on this device.",
					"params": [],
					"tags": [
						{
							"name": "property:readonly"
						},
						{
							"name": "capabilities",
							"x-uses": [
								"xrn:firebolt:capability:localization:language"
							]
						}
					],
					"result": {
						"name": "languages",
						"summary": "The preferred audio languages.",
						"schema": {
							"type": "array",
							"items": {
								"$ref": "#/x-schemas/Localization/ISO639_2Language"
							}
						}
					},
					"examples": [
						{
							"name": "Default example",
							"params": [],
							"result": {
								"name": "Default Result",
								"value": [
									"spa",
									"eng"
								]
							}
						}
					]
				},
				{
					"name": "Localization.locale",
					"tags": [
						{
							"name": "property:readonly"
						},
						{
							"name": "capabilities",
							"x-uses": [
								"xrn:firebolt:capability:localization:locale"
							]
						}
					],
					"summary": "Get the *full* BCP 47 code, including script, region, variant, etc., for the preferred locale",
					"params": [],
					"result": {
						"name": "locale",
						"summary": "The device locale.",
						"schema": {
							"$ref": "#/x-schemas/Localization/Locale"
						}
					},
					"examples": [
						{
							"name": "Default example",
							"params": [],
							"result": {
								"name": "Default Result",
								"value": "en-US"
							}
						}
					]
				},
				{
					"name": "Stats.memoryInfo",
					"summary": "Returns information about container memory usage, in units of 1024 bytes.",
					"tags": [
						{
							"name": "capabilities",
							"x-uses": [
								"xrn:firebolt:capability:accessibility:app"
							]
						}
					],
					"params": [],
					"result": {
						"name": "result",
						"schema": {
							"$ref": "#/components/schemas/MemoryInfo"
						}
					},
					"examples": [
						{
							"name": "Default example",
							"params": [],
							"result": {
								"userMemoryUsedKiB": 123456,
								"userMemoryLimitKiB": 789012,
								"gpuMemoryUsedKiB": 345678,
								"gpuMemoryLimitKiB": 901234
							}
						}
					]
				},
				{
					"name": "Lifecycle2.onStateChanged",
					"tags": [
						{
							"name": "event",
							"x-contextual-parameters": 0,
							"x-notifier": "Lifecycle2.stateChanged"
						},
						{
							"name": "capabilities",
							"x-uses": [
								"xrn:firebolt:capability:lifecycle2:state"
							]
						}
					],
					"summary": "Notification of lifecycle state change, raised after the platform has transitioned the app/runtime to the new lifecycle state",
					"params": [
						{
							"name": "listen",
							"schema": {
								"type": "boolean"
							}
						}
					],
					"examples": [
						{
							"name": "App is active after being initialized",
							"params": [
								{
									"name": "listen",
									"value": true
								}
							],
							"result": {
								"name": "result",
								"value": null
							}
						},
						{
							"name": "Single transition to paused state",
							"params": [
								{
									"name": "listen",
									"value": true
								}
							],
							"result": {
								"name": "result",
								"value": null
							}
						}
					],
					"result": {
						"name": "result",
						"schema": {
							"type": "null"
						}
					}
				},
				{
					"name": "Accessibility.onAudioDescriptionChanged",
					"summary": "Returns the audio description setting of the device",
					"params": [
						{
							"name": "listen",
							"schema": {
								"type": "boolean"
							}
						}
					],
					"tags": [
						{
							"name": "event",
							"x-notifier": "Accessibility.audioDescriptionChanged",
							"x-subscriber-for": "Accessibility.audioDescription"
						},
						{
							"name": "capabilities",
							"x-uses": [
								"xrn:firebolt:capability:accessibility:audiodescriptions"
							]
						}
					],
					"examples": [
						{
							"name": "Getting the audio description setting",
							"params": [
								{
									"name": "listen",
									"value": true
								}
							],
							"result": {
								"name": "result",
								"value": null
							}
						}
					],
					"result": {
						"name": "result",
						"schema": {
							"type": "null"
						}
					}
				},
				{
					"name": "Accessibility.onClosedCaptionsSettingsChanged",
					"summary": "Returns captions settings: enabled, and a list of zero or more languages in order of decreasing preference",
					"params": [
						{
							"name": "listen",
							"schema": {
								"type": "boolean"
							}
						}
					],
					"tags": [
						{
							"name": "event",
							"x-notifier": "Accessibility.closedCaptionsSettingsChanged",
							"x-subscriber-for": "Accessibility.closedCaptionsSettings"
						},
						{
							"name": "capabilities",
							"x-uses": [
								"xrn:firebolt:capability:accessibility:closedcaptions"
							]
						}
					],
					"examples": [
						{
							"name": "Getting the closed captions settings",
							"params": [
								{
									"name": "listen",
									"value": true
								}
							],
							"result": {
								"name": "result",
								"value": null
							}
						}
					],
					"result": {
						"name": "result",
						"schema": {
							"type": "null"
						}
					}
				},
				{
					"name": "Accessibility.onHighContrastUIChanged",
					"summary": "Returns the high contrast UI device setting",
					"params": [
						{
							"name": "listen",
							"schema": {
								"type": "boolean"
							}
						}
					],
					"tags": [
						{
							"name": "event",
							"x-notifier": "Accessibility.highContrastUIChanged",
							"x-subscriber-for": "Accessibility.highContrastUI"
						},
						{
							"name": "capabilities",
							"x-uses": [
								"xrn:firebolt:capability:accessibility:highcontrastui"
							]
						}
					],
					"examples": [
						{
							"name": "High-contrast UI mode is enabled",
							"params": [
								{
									"name": "listen",
									"value": true
								}
							],
							"result": {
								"name": "result",
								"value": null
							}
						}
					],
					"result": {
						"name": "result",
						"schema": {
							"type": "null"
						}
					}
				},
				{
					"name": "Accessibility.onVoiceGuidanceSettingsChanged",
					"summary": "Returns voice guidance settings: enabled, rate, and verbosity",
					"params": [
						{
							"name": "listen",
							"schema": {
								"type": "boolean"
							}
						}
					],
					"tags": [
						{
							"name": "event",
							"x-notifier": "Accessibility.voiceGuidanceSettingsChanged",
							"x-subscriber-for": "Accessibility.voiceGuidanceSettings"
						},
						{
							"name": "capabilities",
							"x-uses": [
								"xrn:firebolt:capability:accessibility:voiceguidance"
							]
						}
					],
					"examples": [
						{
							"name": "Getting the voice guidance settings",
							"params": [
								{
									"name": "listen",
									"value": true
								}
							],
							"result": {
								"name": "result",
								"value": null
							}
						}
					],
					"result": {
						"name": "result",
						"schema": {
							"type": "null"
						}
					}
				},
				{
					"name": "Localization.onCountryChanged",
					"tags": [
						{
							"name": "event",
							"x-notifier": "Localization.countryChanged",
							"x-subscriber-for": "Localization.country"
						},
						{
							"name": "capabilities",
							"x-uses": [
								"xrn:firebolt:capability:localization:country-code"
							]
						}
					],
					"summary": "Returns the ISO 3166-1 alpha-2 code for the country device is located in.",
					"params": [
						{
							"name": "listen",
							"schema": {
								"type": "boolean"
							}
						}
					],
					"examples": [
						{
							"name": "Default example",
							"params": [
								{
									"name": "listen",
									"value": true
								}
							],
							"result": {
								"name": "result",
								"value": null
							}
						},
						{
							"name": "Another example",
							"params": [
								{
									"name": "listen",
									"value": true
								}
							],
							"result": {
								"name": "result",
								"value": null
							}
						}
					],
					"result": {
						"name": "result",
						"schema": {
							"type": "null"
						}
					}
				},
				{
					"name": "Localization.onPreferredAudioLanguagesChanged",
					"summary": "Returns a list of ISO 639-2/B codes for the preferred audio languages on this device.",
					"params": [
						{
							"name": "listen",
							"schema": {
								"type": "boolean"
							}
						}
					],
					"tags": [
						{
							"name": "event",
							"x-notifier": "Localization.preferredAudioLanguagesChanged",
							"x-subscriber-for": "Localization.preferredAudioLanguages"
						},
						{
							"name": "capabilities",
							"x-uses": [
								"xrn:firebolt:capability:localization:language"
							]
						}
					],
					"examples": [
						{
							"name": "Default example",
							"params": [
								{
									"name": "listen",
									"value": true
								}
							],
							"result": {
								"name": "result",
								"value": null
							}
						}
					],
					"result": {
						"name": "result",
						"schema": {
							"type": "null"
						}
					}
				},
				{
					"name": "Localization.onLocaleChanged",
					"tags": [
						{
							"name": "event",
							"x-notifier": "Localization.localeChanged",
							"x-subscriber-for": "Localization.locale"
						},
						{
							"name": "capabilities",
							"x-uses": [
								"xrn:firebolt:capability:localization:locale"
							]
						}
					],
					"summary": "Get the *full* BCP 47 code, including script, region, variant, etc., for the preferred locale",
					"params": [
						{
							"name": "listen",
							"schema": {
								"type": "boolean"
							}
						}
					],
					"examples": [
						{
							"name": "Default example",
							"params": [
								{
									"name": "listen",
									"value": true
								}
							],
							"result": {
								"name": "result",
								"value": null
							}
						}
					],
					"result": {
						"name": "result",
						"schema": {
							"type": "null"
						}
					}
				}
			],
			"components": {
				"schemas": {
					"InitializeResult": {
						"title": "InitializeResult",
						"type": "object",
						"required": [
							"version"
						],
						"properties": {
							"version": {
								"$ref": "#/x-schemas/Types/SemanticVersion",
								"description": "The semantic version of the FEE."
							}
						},
						"additionalProperties": false
					},
					"AdvertisingIdResult": {
						"title": "AdvertisingIdResult",
						"type": "object",
						"properties": {
							"ifa": {
								"type": "string",
								"description": "UUID conforming to IAB standard"
							},
							"ifa_type": {
								"type": "string",
								"description": "Source of the IFA as defined by IAB"
							},
							"lmt": {
								"type": "string",
								"enum": [
									"0",
									"1"
								],
								"description": "Boolean that if set to 1, user has requested ad tracking and measurement is disabled"
							}
						},
						"required": [
							"ifa",
							"ifa_type",
							"lmt"
						]
					},
					"DeviceClass": {
						"title": "DeviceClass",
						"type": "string",
						"enum": [
							"ott",
							"stb",
							"tv"
						],
						"description": "The type of device"
					},
					"CloseType": {
						"title": "CloseType",
						"description": "The application close type",
						"type": "string",
						"enum": [
							"deactivate",
							"unload",
							"killReload",
							"killReactivate"
						]
					},
					"LifecycleState": {
						"title": "LifecycleState",
						"description": "The application Lifecycle state",
						"type": "string",
						"enum": [
							"initializing",
							"active",
							"paused",
							"suspended",
							"hibernated",
							"terminating"
						]
					},
					"StateChange": {
						"title": "StateChange",
						"type": "object",
						"properties": {
							"newState": {
								"$ref": "#/components/schemas/LifecycleState"
							},
							"oldState": {
								"$ref": "#/components/schemas/LifecycleState"
							},
							"focused": {
								"type": "boolean"
							}
						}
					},
					"MemoryInfo": {
						"title": "MemoryInfo",
						"type": "object",
						"description": "Describes current and maximum memory usage of the container.",
						"properties": {
							"userMemoryUsedKiB": {
								"type": "integer",
								"description": "User memory currently used in 1024 bytes."
							},
							"userMemoryLimitKiB": {
								"type": "integer",
								"description": "Maximum user memory available in 1024 bytes."
							},
							"gpuMemoryUsedKiB": {
								"type": "integer",
								"description": "GPU memory currently used in 1024 bytes."
							},
							"gpuMemoryLimitKiB": {
								"type": "integer",
								"description": "Maximum GPU memory available in 1024 bytes."
							}
						},
						"required": [
							"userMemoryUsedKiB",
							"userMemoryLimitKiB",
							"gpuMemoryUsedKiB",
							"gpuMemoryLimitKiB"
						]
					}
				}
			},
			"x-schemas": {
				"Types": {
					"uri": "https://meta.comcast.com/firebolt/types",
					"SemanticVersion": {
						"title": "SemanticVersion",
						"type": "object",
						"properties": {
							"major": {
								"type": "integer",
								"minimum": 0
							},
							"minor": {
								"type": "integer",
								"minimum": 0
							},
							"patch": {
								"type": "integer",
								"minimum": 0
							},
							"readable": {
								"type": "string"
							}
						},
						"required": [
							"major",
							"minor",
							"patch",
							"readable"
						],
						"additionalProperties": false
					}
				},
				"Accessibility": {
					"uri": "https://meta.comcast.com/firebolt/accessibility",
					"ClosedCaptionsSettings": {
						"title": "ClosedCaptionsSettings",
						"type": "object",
						"required": [
							"enabled"
						],
						"properties": {
							"enabled": {
								"type": "boolean",
								"description": "Whether or not closed-captions should be enabled by default"
							},
							"styles": {
								"$ref": "#/x-schemas/Accessibility/ClosedCaptionsStyles"
							},
							"preferredLanguages": {
								"type": "array",
								"items": {
									"$ref": "#/x-schemas/Localization/ISO639_2Language"
								}
							}
						},
						"examples": [
							{
								"enabled": true,
								"styles": {
									"fontFamily": "monospaced_serif",
									"fontSize": 1,
									"fontColor": "#ffffff",
									"fontEdge": "none",
									"fontEdgeColor": "#7F7F7F",
									"fontOpacity": 100,
									"backgroundColor": "#000000",
									"backgroundOpacity": 100,
									"textAlign": "center",
									"textAlignVertical": "middle",
									"windowColor": "white",
									"windowOpacity": 50
								},
								"preferredLanguages": [
									"eng",
									"spa"
								]
							}
						]
					},
					"VoiceGuidanceSettings": {
						"title": "VoiceGuidanceSettings",
						"type": "object",
						"required": [
							"enabled",
							"navigationHints",
							"rate"
						],
						"properties": {
							"enabled": {
								"type": "boolean",
								"description": "Whether or not voice guidance should be enabled by default"
							},
							"rate": {
								"$ref": "#/x-schemas/Accessibility/SpeechRate",
								"description": "The rate at which voice guidance speech will be read back to the user"
							},
							"navigationHints": {
								"type": "boolean",
								"description": "Whether or not voice guidance should include additional navigation hints"
							}
						},
						"examples": [
							{
								"enabled": true,
								"navigationHints": true,
								"rate": 0.8
							}
						]
					},
					"SpeechRate": {
						"title": "SpeechRate",
						"type": "number",
						"minimum": 0.1,
						"maximum": 10
					},
					"ClosedCaptionsStyles": {
						"title": "ClosedCaptionsStyles",
						"type": "object",
						"description": "The default styles to use when displaying closed-captions",
						"properties": {
							"fontFamily": {
								"$ref": "#/x-schemas/Accessibility/FontFamily"
							},
							"fontSize": {
								"$ref": "#/x-schemas/Accessibility/FontSize"
							},
							"fontColor": {
								"$ref": "#/x-schemas/Accessibility/Color"
							},
							"fontEdge": {
								"$ref": "#/x-schemas/Accessibility/FontEdge"
							},
							"fontEdgeColor": {
								"$ref": "#/x-schemas/Accessibility/Color"
							},
							"fontOpacity": {
								"$ref": "#/x-schemas/Accessibility/Opacity"
							},
							"backgroundColor": {
								"$ref": "#/x-schemas/Accessibility/Color"
							},
							"backgroundOpacity": {
								"$ref": "#/x-schemas/Accessibility/Opacity"
							},
							"textAlign": {
								"$ref": "#/x-schemas/Accessibility/HorizontalAlignment"
							},
							"textAlignVertical": {
								"$ref": "#/x-schemas/Accessibility/VerticalAlignment"
							},
							"windowColor": {
								"$ref": "#/x-schemas/Accessibility/Color"
							},
							"windowOpacity": {
								"$ref": "#/x-schemas/Accessibility/Opacity"
							}
						}
					},
					"FontFamily": {
						"type": [
							"string",
							"null"
						],
						"enum": [
							"monospaced_serif",
							"proportional_serif",
							"monospaced_sanserif",
							"proportional_sanserif",
							"smallcaps",
							"cursive",
							"casual",
							null
						]
					},
					"FontSize": {
						"type": [
							"number",
							"null"
						],
						"minimum": 0
					},
					"Color": {
						"type": [
							"string",
							"null"
						]
					},
					"FontEdge": {
						"type": [
							"string",
							"null"
						],
						"enum": [
							"none",
							"raised",
							"depressed",
							"uniform",
							"drop_shadow_left",
							"drop_shadow_right",
							null
						]
					},
					"Opacity": {
						"type": [
							"number",
							"null"
						],
						"minimum": 0,
						"maximum": 100
					},
					"HorizontalAlignment": {
						"type": [
							"string",
							"null"
						]
					},
					"VerticalAlignment": {
						"type": [
							"string",
							"null"
						]
					}
				},
				"Localization": {
					"uri": "https://meta.comcast.com/firebolt/localization",
					"ISO639_2Language": {
						"type": "string",
						"pattern": "^[a-z]{3}$"
					},
					"CountryCode": {
						"type": "string",
						"pattern": "^[A-Z]{2}$"
					},
					"Locale": {
						"type": "string",
						"pattern": "^[a-zA-Z]+([a-zA-Z0-9\\-]*)$"
					}
				}
			}
		}
	}
}