{
    "$id": "https://meta.comcast.com/firebolt/localization",
    "title": "Localization",
    "oneOf": [
        {
            "$ref": "#/definitions/Locality"
        },
        {
            "$ref": "#/definitions/CountryCode"
        },
        {
            "$ref": "#/definitions/Language"
        },
        {
            "$ref": "#/definitions/Locale"
        },
        {
            "$ref": "#/definitions/TimeZone"
        }
    ],
    "definitions": {
        "CountryCode": {
            "type": "string",
            "pattern": "^[A-Za-z]{2}$"
        },
        "Language": {
            "type": "string",
            "pattern": "^[A-Za-z]{2}$"
        },
        "Locality": {
            "type": "string"
        },
        "Locale": {
            "type": "string",
            "pattern": "^[a-zA-Z]+([a-zA-Z0-9\\-]*)$"
        },
        "TimeZone": {
            "type": "string",
            "pattern": "^[-+_\/ A-Za-z 0-9]*$"
        }
    }
}
